verilog_prj/rtl/top.v

module top (
    input  wire clk,
    input  wire rst_n,
    output reg  led
);

    reg [3:0] counter;

    always @(posedge clk) begin
        if (!rst_n) begin
            counter <= 4'd0;
            led     <= 1'b0;
        end else begin
            counter <= counter + 1'b1;

            if (counter == 4'd9)
                led <= ~led;
        end
    end

endmodule

verilog_prj/dump.vcd
$version Generated by VerilatedVcd $end
$timescale 1ps $end
 $scope module TOP $end
  $var wire 1 # clk $end
  $var wire 1 $ rst_n $end
  $var wire 1 % led $end
  $scope module top $end
   $var wire 1 # clk $end
   $var wire 1 $ rst_n $end
   $var wire 1 % led $end
   $var wire 4 & counter [3:0] $end
  $upscope $end
 $upscope $end
$enddefinitions $end


#0
1#
0$
0%
b0000 &
#1
0#
#2
1#
#3
0#
#4
1#
#5
0#
1$
#6
1#
b0001 &
#7
0#
#8
1#
b0010 &
#9
0#
#10
1#
b0011 &
#11
0#
#12
1#
b0100 &
#13
0#
#14
1#
b0101 &
#15
0#
#16
1#
b0110 &
#17
0#
#18
1#
b0111 &
#19
0#
#20
1#
b1000 &
#21
0#
#22
1#
b1001 &
#23
0#
#24
1#
1%
b1010 &
#25
0#
#26
1#
b1011 &
#27
0#
#28
1#
b1100 &
#29
0#
#30
1#
b1101 &
#31
0#
#32
1#
b1110 &
#33
0#
#34
1#
b1111 &
#35
0#
#36
1#
b0000 &
#37
0#
#38
1#
b0001 &
#39
0#
#40
1#
b0010 &
#41
0#
#42
1#
b0011 &
#43
0#
#44
1#
b0100 &
#45
0#
#46
1#
b0101 &
#47
0#
#48
1#
b0110 &
#49
0#
#50
1#
b0111 &
#51
0#
#52
1#
b1000 &
#53
0#
#54
1#
b1001 &
#55
0#
#56
1#
0%
b1010 &
#57
0#
#58
1#
b1011 &
#59
0#
#60
1#
b1100 &
#61
0#
#62
1#
b1101 &
#63
0#
#64
1#
b1110 &
#65
0#
#66
1#
b1111 &
#67
0#
#68
1#
b0000 &
#69
0#
#70
1#
b0001 &
#71
0#
#72
1#
b0010 &
#73
0#
#74
1#
b0011 &
#75
0#
#76
1#
b0100 &
#77
0#
#78
1#
b0101 &
#79
0#
#80
1#
b0110 &
#81
0#
#82
1#
b0111 &
#83
0#
#84
1#
b1000 &
#85
0#
#86
1#
b1001 &
#87
0#
#88
1#
1%
b1010 &
#89
0#
#90
1#
b1011 &
#91
0#
#92
1#
b1100 &
#93
0#
#94
1#
b1101 &
#95
0#
#96
1#
b1110 &
#97
0#
#98
1#
b1111 &
#99
0#
#100
1#
b0000 &
#101
0#
#102
1#
b0001 &
#103
0#
#104
1#
b0010 &
#105
0#
#106
1#
b0011 &
#107
0#
#108
1#
b0100 &
#109
0#
#110
1#
b0101 &
#111
0#
#112
1#
b0110 &
#113
0#
#114
1#
b0111 &
#115
0#
#116
1#
b1000 &
#117
0#
#118
1#
b1001 &
#119
0#
#120
1#
0%
b1010 &
#121
0#
#122
1#
b1011 &
#123
0#
#124
1#
b1100 &
#125
0#
#126
1#
b1101 &
#127
0#
#128
1#
b1110 &
#129
0#
#130
1#
b1111 &
#131
0#
#132
1#
b0000 &
#133
0#
#134
1#
b0001 &
#135
0#
#136
1#
b0010 &
#137
0#
#138
1#
b0011 &
#139
0#
#140
1#
b0100 &
#141
0#
#142
1#
b0101 &
#143
0#
#144
1#
b0110 &
#145
0#
#146
1#
b0111 &
#147
0#
#148
1#
b1000 &
#149
0#
#150
1#
b1001 &
#151
0#
#152
1#
1%
b1010 &
#153
0#
#154
1#
b1011 &
#155
0#
#156
1#
b1100 &
#157
0#
#158
1#
b1101 &
#159
0#
#160
1#
b1110 &
#161
0#
#162
1#
b1111 &
#163
0#
#164
1#
b0000 &
#165
0#
#166
1#
b0001 &
#167
0#
#168
1#
b0010 &
#169
0#
#170
1#
b0011 &
#171
0#
#172
1#
b0100 &
#173
0#
#174
1#
b0101 &
#175
0#
#176
1#
b0110 &
#177
0#
#178
1#
b0111 &
#179
0#
#180
1#
b1000 &
#181
0#
#182
1#
b1001 &
#183
0#
#184
1#
0%
b1010 &
#185
0#
#186
1#
b1011 &
#187
0#
#188
1#
b1100 &
#189
0#
#190
1#
b1101 &
#191
0#
#192
1#
b1110 &
#193
0#
#194
1#
b1111 &
#195
0#
#196
1#
b0000 &
#197
0#
#198
1#
b0001 &
#199
0#
#200
1#
b0010 &
#201
0#
#202
1#
b0011 &
#203
0#
#204
1#
b0100 &
